{"pageContext":{"slug":"/i-may-not-have-gone/","prev":{"id":"2644445f-0377-54c9-bf9d-91b51e839e4e","fields":{"slug":"/i-have-not-failed/","prefix":"2017-10-17","source":"posts"},"frontmatter":{"title":"I have not failed. I've just found 10,000 ways that won't work","category":"testimonies"}},"next":{"id":"98de166b-c595-5524-b3b0-bd5470265831","fields":{"slug":"/like-nonsense/","prefix":"2017-10-21","source":"posts"},"frontmatter":{"title":"I like nonsense, it wakes up the brain cells","category":"testimonies"}},"source":"posts"}}